analytics/__init__.py
analytics/client.py
analytics/consumer.py
analytics/request.py
analytics/utils.py
analytics/version.py
analytics/test/__init__.py
analytics/test/client.py
analytics/test/consumer.py
analytics/test/module.py
analytics/test/request.py
analytics/test/utils.py
segment-0.1.0.dist-info/DESCRIPTION.rst
segment-0.1.0.dist-info/METADATA
segment-0.1.0.dist-info/RECORD
segment-0.1.0.dist-info/WHEEL
segment-0.1.0.dist-info/metadata.json
segment-0.1.0.dist-info/top_level.txt
