Metadata-Version: 2.0
Name: segment
Version: 0.1.0
Summary: The hassle-free way to integrate analytics into any python application.
Home-page: https://github.com/segmentio/analytics-python
Author: Segment
Author-email: friends@segment.com
License: MIT License
Platform: UNKNOWN
Classifier: Development Status :: 5 - Production/Stable
Classifier: Intended Audience :: Developers
Classifier: License :: OSI Approved :: MIT License
Classifier: Operating System :: OS Independent
Classifier: Programming Language :: Python
Classifier: Programming Language :: Python :: 2
Classifier: Programming Language :: Python :: 2.6
Classifier: Programming Language :: Python :: 2.7
Classifier: Programming Language :: Python :: 3
Classifier: Programming Language :: Python :: 3.2
Classifier: Programming Language :: Python :: 3.3
Classifier: Programming Language :: Python :: 3.4
Classifier: Programming Language :: Python :: 3.5
Requires-Dist: python-dateutil (>2.1)
Requires-Dist: requests (>=2.7,<3.0)
Requires-Dist: six (>=1.5)
